pytest_async_mongodb/__init__.py
pytest_async_mongodb/plugin.py
pytest_async_mongodb-0.0.1.dev3.dist-info/DESCRIPTION.rst
pytest_async_mongodb-0.0.1.dev3.dist-info/METADATA
pytest_async_mongodb-0.0.1.dev3.dist-info/RECORD
pytest_async_mongodb-0.0.1.dev3.dist-info/WHEEL
pytest_async_mongodb-0.0.1.dev3.dist-info/entry_points.txt
pytest_async_mongodb-0.0.1.dev3.dist-info/metadata.json
pytest_async_mongodb-0.0.1.dev3.dist-info/pbr.json
pytest_async_mongodb-0.0.1.dev3.dist-info/top_level.txt
