Metadata-Version: 2.0
Name: pytest-async-mongodb
Version: 0.0.1.dev3
Summary: pytest plugin for async MongoDB
Home-page: https://github.com/xzased/pytest-async-mongodb
Author: Ruben Quinones
Author-email: ruben.quinones.gomez@gmail.com
License: MIT
Platform: UNKNOWN
Classifier: Development Status :: 5 - Production/Stable
Classifier: Environment :: Console
Classifier: Intended Audience :: Developers
Classifier: License :: OSI Approved :: MIT License
Classifier: Operating System :: POSIX :: Linux
Classifier: Operating System :: MacOS :: MacOS X
Classifier: Programming Language :: Python
Classifier: Programming Language :: Python :: 3.5
Classifier: Programming Language :: Python :: 3.6
Classifier: Topic :: Database
Classifier: Topic :: Software Development :: Libraries
Requires-Dist: mongomock
Requires-Dist: pyyaml
Requires-Dist: pytest-asyncio
Requires-Dist: pytest (>=2.5.2)
